FakerLibrary/__init__.py
FakerLibrary/keywords.py
robotframework_faker-4.2.0.dist-info/DESCRIPTION.rst
robotframework_faker-4.2.0.dist-info/METADATA
robotframework_faker-4.2.0.dist-info/RECORD
robotframework_faker-4.2.0.dist-info/WHEEL
robotframework_faker-4.2.0.dist-info/metadata.json
robotframework_faker-4.2.0.dist-info/top_level.txt
