Metadata-Version: 1.1
Name: robotframework-faker
Version: 4.2.0
Summary: Robot Framework wrapper for faker, a fake test data generator
Home-page: https://github.com/guykisel/robotframework-faker
Author: Guy Kisel
Author-email: guy.kisel@gmail.com
License: MIT
Download-URL: https://pypi.python.org/pypi/robotframework-faker
Keywords: robotframework testing test automation testautomation atdd bdd faker
Platform: any
Classifier: Development Status :: 5 - Production/Stable
Classifier: License :: OSI Approved :: MIT License
Classifier: Operating System :: OS Independent
Classifier: Programming Language :: Python
Classifier: Programming Language :: Python :: 2
Classifier: Programming Language :: Python :: 2.7
Classifier: Programming Language :: Python :: 3
Classifier: Programming Language :: Python :: 3.3
Classifier: Programming Language :: Python :: 3.4
Classifier: Programming Language :: Python :: 3.6
Classifier: Topic :: Software Development :: Testing
Classifier: Topic :: Software Development :: Quality Assurance
